YehuoFreertosNeiheShixianYuYingyongKaifaShizhan/README.md
YehuoFreertosNeiheShixianYuYingyongKaifaShizhan/__init__.py
YehuoFreertosNeiheShixianYuYingyongKaifaShizhan/__main__.py
YehuoFreertosNeiheShixianYuYingyongKaifaShizhan/file.epub
YehuoFreertosNeiheShixianYuYingyongKaifaShizhan/index.html
YehuoFreertosNeiheShixianYuYingyongKaifaShizhan/css/__init__.py
YehuoFreertosNeiheShixianYuYingyongKaifaShizhan/css/annotations.css
YehuoFreertosNeiheShixianYuYingyongKaifaShizhan/css/main.css
YehuoFreertosNeiheShixianYuYingyongKaifaShizhan/css/normalize.css
YehuoFreertosNeiheShixianYuYingyongKaifaShizhan/css/popup.css
YehuoFreertosNeiheShixianYuYingyongKaifaShizhan/font/__init__.py
YehuoFreertosNeiheShixianYuYingyongKaifaShizhan/font/fontello.eot
YehuoFreertosNeiheShixianYuYingyongKaifaShizhan/font/fontello.svg
YehuoFreertosNeiheShixianYuYingyongKaifaShizhan/font/fontello.ttf
YehuoFreertosNeiheShixianYuYingyongKaifaShizhan/font/fontello.woff
YehuoFreertosNeiheShixianYuYingyongKaifaShizhan/img/__init__.py
YehuoFreertosNeiheShixianYuYingyongKaifaShizhan/img/annotator-glyph-sprite.png
YehuoFreertosNeiheShixianYuYingyongKaifaShizhan/img/annotator-icon-sprite.png
YehuoFreertosNeiheShixianYuYingyongKaifaShizhan/img/apple-touch-icon.png
YehuoFreertosNeiheShixianYuYingyongKaifaShizhan/img/cancelfullscreen.png
YehuoFreertosNeiheShixianYuYingyongKaifaShizhan/img/close.png
YehuoFreertosNeiheShixianYuYingyongKaifaShizhan/img/fullscreen.png
YehuoFreertosNeiheShixianYuYingyongKaifaShizhan/img/loader.gif
YehuoFreertosNeiheShixianYuYingyongKaifaShizhan/img/menu-icon.png
YehuoFreertosNeiheShixianYuYingyongKaifaShizhan/img/save.png
YehuoFreertosNeiheShixianYuYingyongKaifaShizhan/img/saved.png
YehuoFreertosNeiheShixianYuYingyongKaifaShizhan/img/settings-s.png
YehuoFreertosNeiheShixianYuYingyongKaifaShizhan/img/settings.png
YehuoFreertosNeiheShixianYuYingyongKaifaShizhan/img/star.png
YehuoFreertosNeiheShixianYuYingyongKaifaShizhan/js/__init__.py
yehuo_freertos_neihe_shixian_yu_yingyong_kaifa_shizhan-2024.3.5.0.dist-info/METADATA
yehuo_freertos_neihe_shixian_yu_yingyong_kaifa_shizhan-2024.3.5.0.dist-info/WHEEL
yehuo_freertos_neihe_shixian_yu_yingyong_kaifa_shizhan-2024.3.5.0.dist-info/entry_points.txt
yehuo_freertos_neihe_shixian_yu_yingyong_kaifa_shizhan-2024.3.5.0.dist-info/top_level.txt
yehuo_freertos_neihe_shixian_yu_yingyong_kaifa_shizhan-2024.3.5.0.dist-info/RECORD
